{
   "options":{
      "paths":{
         "root":"/opt/tileserver-gl/maptiler-tileserver",
         "fonts":"/opt/tileserver-gl/fonts",
         "styles":"/opt/tileserver-gl/styles",
         "mbtiles":"/opt/tileserver-gl/data",
         "pmtiles":"/opt/pmtiles_converted",
         "icons":"/opt/tileserver-gl/maptiler-tileserver/public/resources/images"

      }
   },
   "styles":{
      "WDB_DARK_MATTER":{
         "style":"WDB_DARK_MATTER/style.json",
         "tilejson":{
            "bounds":[
               -180,
               -85.0511,
               180,
               85.0511
            ]
         }
      },
      "WDB_ELEV":{
         "style":"WDB_ELEV/style.json",
         "tilejson":{
            "bounds":[
               -180,
               -85.0511,
               180,
               85.0511
            ]
         }
      },
      "WDB_BASIC":{
         "style":"WDB_BASIC/style.json",
         "tilejson":{
            "bounds":[
               -180,
               -85.0511,
               180,
               85.0511
            ]
         }
      },
      "WDB_ATV":{
         "style":"WDB_ATV/style.json",
         "tilejson":{
            "bounds":[
               -180,
               -85.0511,
               180,
               85.0511
            ]
         }
      },
      "WDB_GPSTRAILS":{
         "style":"WDB_GPSTRAILS/style.json",
         "tilejson":{
            "bounds":[
               -180,
               -85.0511,
               180,
               85.0511
            ]
         }
      },
      "WDB_OSM_ATV":{
         "style":"WDB_OSM_ATV/style.json",
         "tilejson":{
            "bounds":[
               -180,
               -85.0511,
               180,
               85.0511
            ]
         }
      },
      "WDB_OSM":{
         "style":"WDB_OSM/style.json",
         "tilejson":{
            "bounds":[
               -180,
               -85.0511,
               180,
               85.0511
            ]
         }
      },
      "WDB_OCEAN":{
         "style":"WDB_OCEAN/style.json",
         "tilejson":{
            "bounds":[
               -180,
               -85.0511,
               180,
               85.0511
            ]
         }
      },
      "WDB_SAT":{
         "style":"WDB_SAT/style.json",
         "tilejson":{
            "bounds":[
               -180,
               -85.0511,
               180,
               85.0511
            ]
         }
      },
      "WDB_NO_BACKGROUND":{
         "style":"WDB_NO_BACKGROUND/style.json",
         "tilejson":{
            "bounds":[
               -180,
               -85.0511,
               180,
               85.0511
            ]
         }
      },
      "demotiles":{
         "style":"demotiles/style.json",
         "tilejson":{
            "bounds":[
               -180,
               -85.0511,
               180,
               85.0511
            ]
         }
      },
      "PMTiles_Test":{
         "style":"pmtiles/style.json",
         "tilejson":{
            "bounds":[
               -180,
               -85.0511,
               180,
               85.0511
            ]
         }
      },
      "OpenMapTiles":{
         "style":"OpenMapTiles/style.json",
         "tilejson":{
            "bounds":[
               -180,
               -85.0511,
               180,
               85.0511
            ]
         }
      },
      "protomaps":{
         "style":"protomaps/style.json",
         "tilejson":{
            "bounds":[
               -180,
               -85.0511,
               180,
               85.0511
            ]
         }
      },
      "WDB_BASIC_OVERTURE":{
         "style":"WDB_BASIC_OVERTURE/style.json",
         "tilejson":{
            "bounds":[
               -180,
               -85.0511,
               180,
               85.0511
            ]
         }
      }
   },
   "data":{
      "ne_basemap":{
         "mbtiles":"ne_basemap.mbtiles"
      },
      "WifiDB_newest":{
         "mbtiles":"WifiDB_newest.mbtiles"
      },
      "WifiDB":{
         "mbtiles":"WifiDB.mbtiles"
      },
      "openmaptiles":{
         "pmtiles":"planetiler-openmaptiles-latest.pmtiles"
      },
      "WifiDB_cells":{
         "mbtiles":"cell_networks.mbtiles"
      },
      "jaxa_color":{
         "pmtiles":"jaxa_color.pmtiles"
      },
      "jaxa_hillshade":{
         "mbtiles":"jaxa_hillshade.mbtiles"
      },
      "jaxa_terrainrgb_webp":{
         "mbtiles":"jaxa_terrainrgb_Z0-12_webp.mbtiles"
      },
      "jaxa_terrainrgb":{
         "pmtiles":"jaxa_terrainrgb0-12.pmtiles"
      },
      "jaxa_terrarium":{
         "pmtiles":"jaxa_terrarium0-11_v2.pmtiles"
      },
      "osm_basemap":{
         "mbtiles":"osm_basemap.mbtiles"
      },
      "atv":{
         "mbtiles":"offroad_trails.mbtiles"
      },
      "contour_250m":{
         "mbtiles":"contour_250m.mbtiles"
      },
      "demotiles":{
         "mbtiles":"demotiles.mbtiles"
      },
      "landcover":{
         "mbtiles":"landcover.mbtiles"
      },
      "NE2":{
         "mbtiles":"NE2_HR_LC_SR_W_DR.mbtiles"
      },
      "atv-trails":{
         "mbtiles":"atv-trails.mbtiles"
      },
      "atv-points":{
         "mbtiles":"atv-points.mbtiles"
      },
      "ocean-rgb":{
         "mbtiles":"gebco_terrainrgb0-9.mbtiles"
      },
      "ocean-rgb-2":{
         "mbtiles":"gebco_terrainrgb0-8.mbtiles"
      },
      "gebco_color_releif":{
         "mbtiles":"gebco_color_releif.mbtiles"
      },
      "gebco_terrarium0-8":{
         "mbtiles":"gebco_terrarium0-8.mbtiles"
      },
      "swissalti3d_terrarium_0-17":{
         "mbtiles":"swissalti3d_terrarium0-17.mbtiles"
      },
      "gebco_color_releif_pmtiles":{
         "pmtiles":"gebco_color_releif.pmtiles"
      },
      "jaxa_color_pmtiles":{
         "pmtiles":"jaxa_color.pmtiles"
      },
      "osm_basemap_pmtiles":{
         "pmtiles":"osm_basemap.pmtiles"
      },
      "planetiler_2023-09-02_pmtiles":{
         "pmtiles":"planetiler_2023-09-02.pmtiles"
      },
      "planetiler-0-7-0_pmtiles":{
         "pmtiles":"planetiler-0-7-0.pmtiles"
      },
      "gebco_terrarium0-8_pmtiles":{
         "pmtiles":"gebco_terrarium0-8.pmtiles"
      },
      "protomaps":{
         "pmtiles":"planetiler-protomaps-latest.pmtiles"
      },
      "overture":{
         "pmtiles":"overture-2023-12-14-alpha.0.pmtiles"
      }
   }
}
